glask/__init__.py
glask/glask.py
glask/middleware.py
glask/util/__init__.py
glask/util/request.py
glask/util/response.py
glask_swh-0.0.1.dist-info/METADATA
glask_swh-0.0.1.dist-info/WHEEL
glask_swh-0.0.1.dist-info/top_level.txt
glask_swh-0.0.1.dist-info/RECORD
